corona/__init__.py
corona/main.py
corona-app/__init__.py
corona-app/main.py
corona_app-0.0.4.dist-info/LICENSE
corona_app-0.0.4.dist-info/METADATA
corona_app-0.0.4.dist-info/WHEEL
corona_app-0.0.4.dist-info/top_level.txt
corona_app-0.0.4.dist-info/zip-safe
corona_app-0.0.4.dist-info/RECORD
