Metadata-Version: 2.1
Name: corona-app
Version: 0.0.4
Summary: Python Library for CORONA APP
Home-page: https://github.com/yuyatinnefeld/corona-app
Author: yuya tinnefeld
Author-email: yuyatinnefeld@gmail.com
License: Copyright (c) 2022 Yuya Tinnefeld
Platform: UNKNOWN
Classifier: Development Status :: 3 - Alpha
Classifier: Programming Language :: Python :: 3.7
Requires-Python: >=3.7
License-File: LICENSE
Requires-Dist: requests (==2.26.0)
